coexist.py
python_coexist-0.1.1.dist-info/licenses/LICENSE
python_coexist-0.1.1.dist-info/METADATA
python_coexist-0.1.1.dist-info/WHEEL
python_coexist-0.1.1.dist-info/top_level.txt
python_coexist-0.1.1.dist-info/RECORD
