Metadata-Version: 2.4
Name: python-coexist
Version: 0.1.1
Summary: Run multiple code statements concurrently using a simple and Pythonic context manager
Author-email: Omer Menashe <unspecified@mail.com>
License: MIT
Project-URL: Source, https://github.com/iamomerm/python-coexist
Keywords: python-coexist,coexist
Classifier: Programming Language :: Python :: 3
Classifier: License :: OSI Approved :: MIT License
Classifier: Operating System :: OS Independent
Requires-Python: >=3.7
License-File: LICENSE
Dynamic: license-file
